brent_search/__init__.py
brent_search/_bracket.py
brent_search/_brent.py
brent_search/_optimize.py
brent_search/_testit.py
brent_search-2.0.2.dist-info/LICENSE.md
brent_search-2.0.2.dist-info/METADATA
brent_search-2.0.2.dist-info/WHEEL
brent_search-2.0.2.dist-info/RECORD
